pywebapp/__init__.py
pywebapp/__main__.py
pywebapp/app.py
pywebapp/bridge.py
pywebapp/log.py
pywebapp/main.py
pywebapp/photostyle.py
pywebapp/run.py
pywebapp/_app/__init__.py
pywebapp/builder/__init__.py
pywebapp/py_ts/__init__.py
pywebapp/py_ts/clf.py
pywebapp/py_ts/type_map.py
pywebapp-0.0.0.dist-info/METADATA
pywebapp-0.0.0.dist-info/WHEEL
pywebapp-0.0.0.dist-info/top_level.txt
pywebapp-0.0.0.dist-info/RECORD
