Metadata-Version: 2.4
Name: pywebapp
Version: 0.0.0
Summary: Add your description here
Requires-Python: >=3.12
Requires-Dist: loguru>=0.7.3
Requires-Dist: pyinstaller>=6.14.1
Requires-Dist: pywebview>=5.4
Requires-Dist: typer>=0.16.0
Requires-Dist: watchdog>=6.0.0
